{
  "metric": {
    "__name__": "net_peers", 
    "job": "openethereum", 
    "instance": "172.17.0.1:3033"
  }, 
  "values": [
    [
      1627484227, 
      "31"
    ], 
    [
      1627484242, 
      "25"
    ], 
    [
      1627484257, 
      "25"
    ], 
    [
      1627484272, 
      "24"
    ], 
    [
      1627484287, 
      "22"
    ], 
    [
      1627484302, 
      "22"
    ], 
    [
      1627484317, 
      "20"
    ], 
    [
      1627484332, 
      "18"
    ], 
    [
      1627484347, 
      "14"
    ], 
    [
      1627484362, 
      "10"
    ], 
    [
      1627484377, 
      "10"
    ], 
    [
      1627484392, 
      "9"
    ], 
    [
      1627484407, 
      "12"
    ], 
    [
      1627484422, 
      "14"
    ], 
    [
      1627484437, 
      "10"
    ], 
    [
      1627484452, 
      "12"
    ], 
    [
      1627484467, 
      "16"
    ], 
    [
      1627484482, 
      "13"
    ], 
    [
      1627484497, 
      "14"
    ], 
    [
      1627484512, 
      "18"
    ], 
    [
      1627484527, 
      "15"
    ]
  ], 
  "stat": {
    "max": 25.0, 
    "mean": 16.857142857142858, 
    "variance": 35.36054421768707, 
    "min": 10.0
  }
}