{
  "metric": {
    "__name__": "net_peers", 
    "job": "openethereum", 
    "instance": "172.17.0.1:3033"
  }, 
  "values": [
    [
      1622764026, 
      "40"
    ], 
    [
      1622764041, 
      "40"
    ], 
    [
      1622764056, 
      "40"
    ], 
    [
      1622764071, 
      "41"
    ], 
    [
      1622764086, 
      "41"
    ], 
    [
      1622764101, 
      "42"
    ], 
    [
      1622764116, 
      "42"
    ], 
    [
      1622764131, 
      "42"
    ], 
    [
      1622764146, 
      "42"
    ], 
    [
      1622764161, 
      "42"
    ], 
    [
      1622764176, 
      "40"
    ], 
    [
      1622764191, 
      "40"
    ], 
    [
      1622764206, 
      "40"
    ], 
    [
      1622764221, 
      "39"
    ], 
    [
      1622764236, 
      "39"
    ], 
    [
      1622764251, 
      "40"
    ], 
    [
      1622764266, 
      "40"
    ], 
    [
      1622764281, 
      "42"
    ], 
    [
      1622764296, 
      "42"
    ], 
    [
      1622764311, 
      "42"
    ], 
    [
      1622764326, 
      "42"
    ]
  ], 
  "stat": {
    "max": 42.0, 
    "mean": 40.857142857142854, 
    "variance": 1.1700680272108848, 
    "min": 39.0
  }
}