{
  "dir_read_c": {
    "metric": {
      "instance": "172.17.0.1:8000", 
      "hostname": "longz-chaosevm", 
      "pid": "27348", 
      "directory": "/data/eth-data", 
      "job": "syscall_monitoring", 
      "application_name": "geth", 
      "__name__": "dir_reads_total"
    }, 
    "values": [
      [
        1633134510, 
        "130682"
      ], 
      [
        1633134525, 
        "54315"
      ], 
      [
        1633134540, 
        "75877"
      ], 
      [
        1633134555, 
        "71247"
      ], 
      [
        1633134570, 
        "19817"
      ], 
      [
        1633134585, 
        "27286"
      ], 
      [
        1633134600, 
        "35905"
      ], 
      [
        1633134615, 
        "32137"
      ], 
      [
        1633134630, 
        "29202"
      ], 
      [
        1633134645, 
        "30183"
      ], 
      [
        1633134660, 
        "29216"
      ], 
      [
        1633134675, 
        "29863"
      ], 
      [
        1633134690, 
        "28969"
      ], 
      [
        1633134705, 
        "28073"
      ], 
      [
        1633134720, 
        "26179"
      ], 
      [
        1633134735, 
        "23494"
      ], 
      [
        1633134750, 
        "25788"
      ], 
      [
        1633134765, 
        "19889"
      ], 
      [
        1633134780, 
        "17154"
      ], 
      [
        1633134795, 
        "17858"
      ], 
      [
        1633134810, 
        "17460"
      ]
    ]
  }, 
  "stat": {
    "dir_read_c": {
      "max": 75877.0, 
      "mean": 36694.95238095238, 
      "variance": 685524012.4263039, 
      "pvalue": 1.1810947476625239e-05, 
      "min": 17460.0
    }, 
    "dir_reads": {
      "max": 1126128640.0, 
      "mean": 471886799.2380952, 
      "variance": 1.7520974765951818e+17, 
      "pvalue": 1.5339852216572332e-05, 
      "min": 211668992.0
    }, 
    "tcp_conn": {
      "max": 58.0, 
      "mean": 37.857142857142854, 
      "variance": 77.45578231292515, 
      "pvalue": 1.6526653304976648e-19, 
      "min": 31.0
    }, 
    "tcp_sends": {
      "max": 8958976.0, 
      "mean": 1382302.4761904762, 
      "variance": 8811982134757.295, 
      "pvalue": 0.0034012418206862656, 
      "min": 53248.0
    }, 
    "dir_writes": {
      "max": 104448.0, 
      "mean": 35596.19047619047, 
      "variance": 2006365766.8208613, 
      "pvalue": 1.0997774848732021e-06, 
      "min": 2048.0
    }, 
    "dir_write_c": {
      "max": 235.0, 
      "mean": 120.0, 
      "variance": 9343.52380952381, 
      "pvalue": 0.00013566842018169936, 
      "min": 21.0
    }, 
    "disk_write": {
      "max": 62138.24766152091, 
      "mean": 18894.973372711323, 
      "variance": 441766574.2243907, 
      "pvalue": 0.19058146920009533, 
      "min": 2803.821212818479
    }, 
    "disk_read": {
      "max": 53582143.86319802, 
      "mean": 31837408.41251109, 
      "variance": 141999957140690.44, 
      "pvalue": 1.8164021772313931e-07, 
      "min": 18442526.186337158
    }, 
    "peer_stats": {
      "max": 35.074999999999996, 
      "mean": 30.875, 
      "variance": 10.746875, 
      "pvalue": 1.2026467019345983e-18, 
      "min": 24.475
    }, 
    "tcp_recvs": {
      "max": 4102144.0, 
      "mean": 1551847.619047619, 
      "variance": 1441634875285.188, 
      "pvalue": 1.0997774848732021e-06, 
      "min": 487424.0
    }
  }, 
  "dir_reads": {
    "metric": {
      "instance": "172.17.0.1:8000", 
      "hostname": "longz-chaosevm", 
      "pid": "27348", 
      "directory": "/data/eth-data", 
      "job": "syscall_monitoring", 
      "application_name": "geth"
    }, 
    "values": [
      [
        1633134510, 
        "1976441856"
      ], 
      [
        1633134525, 
        "717342720"
      ], 
      [
        1633134540, 
        "1126128640"
      ], 
      [
        1633134555, 
        "1066738688"
      ], 
      [
        1633134570, 
        "244926464"
      ], 
      [
        1633134585, 
        "299468800"
      ], 
      [
        1633134600, 
        "383854592"
      ], 
      [
        1633134615, 
        "350809088"
      ], 
      [
        1633134630, 
        "324510720"
      ], 
      [
        1633134645, 
        "337067008"
      ], 
      [
        1633134660, 
        "326884352"
      ], 
      [
        1633134675, 
        "333189120"
      ], 
      [
        1633134690, 
        "326345728"
      ], 
      [
        1633134705, 
        "317298688"
      ], 
      [
        1633134720, 
        "301983744"
      ], 
      [
        1633134735, 
        "296428544"
      ], 
      [
        1633134750, 
        "306648064"
      ], 
      [
        1633134765, 
        "240917504"
      ], 
      [
        1633134780, 
        "207067136"
      ], 
      [
        1633134795, 
        "213902336"
      ], 
      [
        1633134810, 
        "211668992"
      ]
    ]
  }, 
  "tcp_conn": {
    "metric": {}, 
    "values": [
      [
        1633134510, 
        "67"
      ], 
      [
        1633134525, 
        "58"
      ], 
      [
        1633134540, 
        "43"
      ], 
      [
        1633134555, 
        "39"
      ], 
      [
        1633134570, 
        "37"
      ], 
      [
        1633134585, 
        "39"
      ], 
      [
        1633134600, 
        "36"
      ], 
      [
        1633134615, 
        "33"
      ], 
      [
        1633134630, 
        "35"
      ], 
      [
        1633134645, 
        "38"
      ], 
      [
        1633134660, 
        "37"
      ], 
      [
        1633134675, 
        "38"
      ], 
      [
        1633134690, 
        "35"
      ], 
      [
        1633134705, 
        "35"
      ], 
      [
        1633134720, 
        "34"
      ], 
      [
        1633134735, 
        "35"
      ], 
      [
        1633134750, 
        "33"
      ], 
      [
        1633134765, 
        "35"
      ], 
      [
        1633134780, 
        "31"
      ], 
      [
        1633134795, 
        "31"
      ], 
      [
        1633134810, 
        "26"
      ]
    ]
  }, 
  "tcp_sends": {
    "metric": {}, 
    "values": [
      [
        1633134510, 
        "136192"
      ], 
      [
        1633134525, 
        "57344"
      ], 
      [
        1633134540, 
        "113664"
      ], 
      [
        1633134555, 
        "53248"
      ], 
      [
        1633134570, 
        "107520"
      ], 
      [
        1633134585, 
        "56320"
      ], 
      [
        1633134600, 
        "1651712"
      ], 
      [
        1633134615, 
        "8958976"
      ], 
      [
        1633134630, 
        "671744"
      ], 
      [
        1633134645, 
        "59392"
      ], 
      [
        1633134660, 
        "106496"
      ], 
      [
        1633134675, 
        "55296"
      ], 
      [
        1633134690, 
        "147456"
      ], 
      [
        1633134705, 
        "71680"
      ], 
      [
        1633134720, 
        "116736"
      ], 
      [
        1633134735, 
        "10183680"
      ], 
      [
        1633134750, 
        "6155264"
      ], 
      [
        1633134765, 
        "53248"
      ], 
      [
        1633134780, 
        "110592"
      ], 
      [
        1633134795, 
        "54272"
      ], 
      [
        1633134810, 
        "107520"
      ]
    ]
  }, 
  "dir_writes": {
    "metric": {
      "instance": "172.17.0.1:8000", 
      "hostname": "longz-chaosevm", 
      "pid": "27348", 
      "directory": "/data/eth-data", 
      "job": "syscall_monitoring", 
      "application_name": "geth"
    }, 
    "values": [
      [
        1633134510, 
        "2048"
      ], 
      [
        1633134525, 
        "26624"
      ], 
      [
        1633134540, 
        "2048"
      ], 
      [
        1633134555, 
        "27648"
      ], 
      [
        1633134570, 
        "1024"
      ], 
      [
        1633134585, 
        "25600"
      ], 
      [
        1633134600, 
        "3072"
      ], 
      [
        1633134615, 
        "27648"
      ], 
      [
        1633134630, 
        "4096"
      ], 
      [
        1633134645, 
        "28672"
      ], 
      [
        1633134660, 
        "2048"
      ], 
      [
        1633134675, 
        "28672"
      ], 
      [
        1633134690, 
        "104448"
      ], 
      [
        1633134705, 
        "193536"
      ], 
      [
        1633134720, 
        "71680"
      ], 
      [
        1633134735, 
        "82944"
      ], 
      [
        1633134750, 
        "3072"
      ], 
      [
        1633134765, 
        "32768"
      ], 
      [
        1633134780, 
        "37888"
      ], 
      [
        1633134795, 
        "34816"
      ], 
      [
        1633134810, 
        "7168"
      ]
    ]
  }, 
  "dir_write_c": {
    "metric": {
      "instance": "172.17.0.1:8000", 
      "hostname": "longz-chaosevm", 
      "pid": "27348", 
      "directory": "/data/eth-data", 
      "job": "syscall_monitoring", 
      "application_name": "geth", 
      "__name__": "dir_writes_total"
    }, 
    "values": [
      [
        1633134510, 
        "26"
      ], 
      [
        1633134525, 
        "196"
      ], 
      [
        1633134540, 
        "18"
      ], 
      [
        1633134555, 
        "209"
      ], 
      [
        1633134570, 
        "21"
      ], 
      [
        1633134585, 
        "199"
      ], 
      [
        1633134600, 
        "24"
      ], 
      [
        1633134615, 
        "208"
      ], 
      [
        1633134630, 
        "31"
      ], 
      [
        1633134645, 
        "219"
      ], 
      [
        1633134660, 
        "25"
      ], 
      [
        1633134675, 
        "211"
      ], 
      [
        1633134690, 
        "45"
      ], 
      [
        1633134705, 
        "235"
      ], 
      [
        1633134720, 
        "33"
      ], 
      [
        1633134735, 
        "219"
      ], 
      [
        1633134750, 
        "31"
      ], 
      [
        1633134765, 
        "218"
      ], 
      [
        1633134780, 
        "47"
      ], 
      [
        1633134795, 
        "283"
      ], 
      [
        1633134810, 
        "22"
      ]
    ]
  }, 
  "disk_write": {
    "values": [
      [
        1633134510, 
        78912.04186267921
      ], 
      [
        1633134525, 
        61255.416387775724
      ], 
      [
        1633134540, 
        47877.51722519831
      ], 
      [
        1633134555, 
        37166.13346100717
      ], 
      [
        1633134570, 
        29045.57553868198
      ], 
      [
        1633134585, 
        22565.83652002322
      ], 
      [
        1633134600, 
        17641.800734216908
      ], 
      [
        1633134615, 
        13712.743354021652
      ], 
      [
        1633134630, 
        10733.632303873474
      ], 
      [
        1633134645, 
        8335.862375023606
      ], 
      [
        1633134660, 
        6520.540848751232
      ], 
      [
        1633134675, 
        6544.983161388757
      ], 
      [
        1633134690, 
        7080.778470400632
      ], 
      [
        1633134705, 
        6833.033552179378
      ], 
      [
        1633134720, 
        6214.640790737477
      ], 
      [
        1633134735, 
        4923.953820829032
      ], 
      [
        1633134750, 
        3916.5531348184895
      ], 
      [
        1633134765, 
        3538.793016354729
      ], 
      [
        1633134780, 
        2833.1551866724526
      ], 
      [
        1633134795, 
        2246.475709592982
      ]
    ], 
    "name": "geth.eth/db/chaindata/disk/write.meter", 
    "columns": [
      "time", 
      "mean"
    ]
  }, 
  "disk_read": {
    "values": [
      [
        1633134510, 
        48732960.24787104
      ], 
      [
        1633134525, 
        53437924.95801181
      ], 
      [
        1633134540, 
        56322303.061735846
      ], 
      [
        1633134555, 
        48751529.071423955
      ], 
      [
        1633134570, 
        42839033.677493565
      ], 
      [
        1633134585, 
        38145875.174912095
      ], 
      [
        1633134600, 
        35546650.9611453
      ], 
      [
        1633134615, 
        32054338.852044415
      ], 
      [
        1633134630, 
        30320591.87365741
      ], 
      [
        1633134645, 
        28007164.013672054
      ], 
      [
        1633134660, 
        27154182.428699285
      ], 
      [
        1633134675, 
        25389782.32657709
      ], 
      [
        1633134690, 
        25045250.91029287
      ], 
      [
        1633134705, 
        23644547.688515183
      ], 
      [
        1633134720, 
        23002491.444205966
      ], 
      [
        1633134735, 
        22050884.026399236
      ], 
      [
        1633134750, 
        21279112.009196088
      ], 
      [
        1633134765, 
        19305457.882709283
      ], 
      [
        1633134780, 
        18507357.56028243
      ], 
      [
        1633134795, 
        17210730.08137694
      ]
    ], 
    "name": "geth.eth/db/chaindata/disk/read.meter", 
    "columns": [
      "time", 
      "mean"
    ]
  }, 
  "peer_stats": {
    "values": [
      [
        1633134510, 
        36.5
      ], 
      [
        1633134525, 
        35
      ], 
      [
        1633134540, 
        35
      ], 
      [
        1633134555, 
        34
      ], 
      [
        1633134570, 
        33.5
      ], 
      [
        1633134585, 
        32
      ], 
      [
        1633134600, 
        32
      ], 
      [
        1633134615, 
        32
      ], 
      [
        1633134630, 
        32
      ], 
      [
        1633134645, 
        32
      ], 
      [
        1633134660, 
        32
      ], 
      [
        1633134675, 
        32
      ], 
      [
        1633134690, 
        29.5
      ], 
      [
        1633134705, 
        29
      ], 
      [
        1633134720, 
        28.5
      ], 
      [
        1633134735, 
        28
      ], 
      [
        1633134750, 
        28
      ], 
      [
        1633134765, 
        28
      ], 
      [
        1633134780, 
        24.5
      ], 
      [
        1633134795, 
        24
      ]
    ], 
    "name": "geth.p2p/peers.gauge", 
    "columns": [
      "time", 
      "median"
    ]
  }, 
  "tcp_recvs": {
    "metric": {}, 
    "values": [
      [
        1633134510, 
        "5097472"
      ], 
      [
        1633134525, 
        "1364992"
      ], 
      [
        1633134540, 
        "1572864"
      ], 
      [
        1633134555, 
        "907264"
      ], 
      [
        1633134570, 
        "487424"
      ], 
      [
        1633134585, 
        "575488"
      ], 
      [
        1633134600, 
        "4102144"
      ], 
      [
        1633134615, 
        "1977344"
      ], 
      [
        1633134630, 
        "1627136"
      ], 
      [
        1633134645, 
        "947200"
      ], 
      [
        1633134660, 
        "454656"
      ], 
      [
        1633134675, 
        "1251328"
      ], 
      [
        1633134690, 
        "3132416"
      ], 
      [
        1633134705, 
        "2426880"
      ], 
      [
        1633134720, 
        "1304576"
      ], 
      [
        1633134735, 
        "1564672"
      ], 
      [
        1633134750, 
        "671744"
      ], 
      [
        1633134765, 
        "795648"
      ], 
      [
        1633134780, 
        "1249280"
      ], 
      [
        1633134795, 
        "561152"
      ], 
      [
        1633134810, 
        "517120"
      ]
    ]
  }
}