{
  "metric": {
    "__name__": "net_peers", 
    "job": "openethereum", 
    "instance": "172.17.0.1:3033"
  }, 
  "values": [
    [
      1627474589, 
      "27"
    ], 
    [
      1627474604, 
      "27"
    ], 
    [
      1627474619, 
      "27"
    ], 
    [
      1627474634, 
      "27"
    ], 
    [
      1627474649, 
      "26"
    ], 
    [
      1627474664, 
      "26"
    ], 
    [
      1627474679, 
      "26"
    ], 
    [
      1627474694, 
      "26"
    ], 
    [
      1627474709, 
      "26"
    ], 
    [
      1627474724, 
      "25"
    ], 
    [
      1627474739, 
      "25"
    ], 
    [
      1627474754, 
      "25"
    ], 
    [
      1627474769, 
      "27"
    ], 
    [
      1627474784, 
      "25"
    ], 
    [
      1627474799, 
      "26"
    ], 
    [
      1627474814, 
      "26"
    ], 
    [
      1627474829, 
      "26"
    ], 
    [
      1627474844, 
      "26"
    ], 
    [
      1627474859, 
      "27"
    ], 
    [
      1627474874, 
      "27"
    ], 
    [
      1627474889, 
      "26"
    ]
  ], 
  "stat": {
    "max": 27.0, 
    "mean": 26.142857142857142, 
    "variance": 0.5034013605442178, 
    "min": 25.0
  }
}